stackit/secretsmanager/__init__.py
stackit/secretsmanager/api/__init__.py
stackit/secretsmanager/api/default_api.py
stackit/secretsmanager/api_client.py
stackit/secretsmanager/api_response.py
stackit/secretsmanager/configuration.py
stackit/secretsmanager/exceptions.py
stackit/secretsmanager/models/__init__.py
stackit/secretsmanager/models/acl.py
stackit/secretsmanager/models/bad_request.py
stackit/secretsmanager/models/conflict.py
stackit/secretsmanager/models/create_acl_payload.py
stackit/secretsmanager/models/create_instance_payload.py
stackit/secretsmanager/models/create_user_payload.py
stackit/secretsmanager/models/instance.py
stackit/secretsmanager/models/kms_key_payload.py
stackit/secretsmanager/models/list_acls_response.py
stackit/secretsmanager/models/list_instances_response.py
stackit/secretsmanager/models/list_users_response.py
stackit/secretsmanager/models/not_found.py
stackit/secretsmanager/models/update_acl_payload.py
stackit/secretsmanager/models/update_acls_payload.py
stackit/secretsmanager/models/update_instance_payload.py
stackit/secretsmanager/models/update_user_payload.py
stackit/secretsmanager/models/user.py
stackit/secretsmanager/py.typed
stackit/secretsmanager/rest.py
stackit_secretsmanager-0.4.0.dist-info/METADATA
stackit_secretsmanager-0.4.0.dist-info/WHEEL
stackit_secretsmanager-0.4.0.dist-info/licenses/LICENSE.md
stackit_secretsmanager-0.4.0.dist-info/licenses/NOTICE.txt
stackit_secretsmanager-0.4.0.dist-info/RECORD
